Metadata-Version: 1.1
Name: django-notify-x
Version: 0.1.9
Summary: Notification sytem for Django
Home-page: https://github.com/v1k45/django-notify-x
Author: Vikas Yadav
Author-email: v1k45x@gmail.com
License: The MIT License
Keywords: django notifications,notify,facebook like notifications
Platform: OS Independent
Classifier: Development Status :: 5 - Production/Stable
Classifier: Framework :: Django :: 1.8
Classifier: Framework :: Django :: 1.9
Classifier: Framework :: Django :: 1.10
Classifier: Framework :: Django :: 1.11
Classifier: Framework :: Django :: 2.0
Classifier: Environment :: Web Environment
Classifier: Operating System :: OS Independent
Classifier: Programming Language :: Python :: 2.7
Classifier: Programming Language :: Python :: 3.4
Classifier: Intended Audience :: Developers
